{
  "project_info": {
    "project_number": "782519850257",
    "project_id": "flutter-crud-4a348",
    "storage_bucket": "flutter-crud-4a348.appspot.com"
  },
  "client": [
    {
      "client_info": {
        "mobilesdk_app_id": "1:782519850257:android:2aadb114e619559ad168b0",
        "android_client_info": {
          "package_name": "com.example.flutter_crud"
        }
      },
      "oauth_client": [
        {
          "client_id": "782519850257-9h5pr6uret7es1quqn0h27djkf1kb5jc.apps.googleusercontent.com",
          "client_type": 3
        }
      ],
      "api_key": [
        {
          "current_key": "AIzaSyCtA-H1FhQP1wKhymuqyH2IaCSGw3L0KUE"
        }
      ],
      "services": {
        "appinvite_service": {
          "other_platform_oauth_client": [
            {
              "client_id": "782519850257-9h5pr6uret7es1quqn0h27djkf1kb5jc.apps.googleusercontent.com",
              "client_type": 3
            }
          ]
        }
      }
    }
  ],
  "configuration_version": "1"
}